yotuyu/__init__.py
yotuyu/estimator.py
yotuyu/loader.py
yotuyu/logger.py
yotuyu/params.py
yotuyu/preprocessor.py
yotuyu-0.0.1.dev0.dist-info/WHEEL
yotuyu-0.0.1.dev0.dist-info/METADATA
yotuyu-0.0.1.dev0.dist-info/RECORD
